Metadata-Version: 2.1
Name: biodivmap
Version: 0.0.7
Summary: Biodiversity mapping
Author: Zijie Wang
